gator/__init__.py
gator/__main__.py
gator/constants.py
gator/exceptions.py
gator/post_process.py
gator/pre_process.py
gator/resources/__init__.py
gator/resources/build.py
gator/resources/models.py
gator/resources/util.py
gator/resources/code_changes/__init__.py
gator/resources/code_changes/new_file.py
gator/resources/code_changes/regex_replace.py
gator/resources/code_changes/remove_file.py
gator/resources/filters/__init__.py
gator/resources/filters/regex_filter.py
tests/__init__.py
tests/conftest.py
tests/test_main.py
tests/resources/__init__.py
tests/resources/test_build.py
tests/resources/test_util.py
tests/resources/filters/__init__.py
tests/resources/filters/test_regex_filter.py
gator-0.0.1.dist-info/LICENSE
gator-0.0.1.dist-info/METADATA
gator-0.0.1.dist-info/WHEEL
gator-0.0.1.dist-info/top_level.txt
gator-0.0.1.dist-info/RECORD
