Metadata-Version: 2.1
Name: gator
Version: 0.0.1
Summary: Change Propagator
Home-page: https://github.com/wayfair-incubator/gator
Author: Jack Pierce
Author-email: jackhpierce@gmail.com
License: UNKNOWN
Platform: UNKNOWN
Classifier: Development Status :: 4 - Beta
Classifier: Programming Language :: Python
Classifier: Programming Language :: Python :: 3
Classifier: Programming Language :: Python :: 3.8
Classifier: Programming Language :: Python :: 3.9
Classifier: Programming Language :: Python :: 3.10
Classifier: License :: OSI Approved :: MIT License
Classifier: Operating System :: OS Independent
Requires-Python: >=3.6
License-File: LICENSE
Requires-Dist: GitPython (<3.2,>=3.1)
